{
  "$schema": "https://developer.microsoft.com/json-schemas/spfx-build/package-solution.schema.json",
  "solution": {
    "name": "spfx-ci-cd-client-side-solution",
    "id": "5a474b42-3071-448e-bad5-7a35b8dac26d",
    "version": "0.0.2.0",
    "includeClientSideAssets": true,
    "skipFeatureDeployment": true,
    "isDomainIsolated": false,
    "developer": {
      "name": "",
      "websiteUrl": "",
      "privacyUrl": "",
      "termsOfUseUrl": "",
      "mpnId": "Undefined-1.17.3"
    },
    "metadata": {
      "shortDescription": {
        "default": "spfx-ci-cd description"
      },
      "longDescription": {
        "default": "spfx-ci-cd description"
      },
      "screenshotPaths": [],
      "videoUrl": "",
      "categories": []
    },
    "features": [
      {
        "title": "spfx-ci-cd Feature",
        "description": "The feature that activates elements of the spfx-ci-cd solution.",
        "id": "cf5e26c6-9806-4848-9aac-709c21f52f5b",
        "version": "0.0.2.0"
      }
    ]
  },
  "paths": {
    "zippedPackage": "solution/spfx-ci-cd.sppkg"
  }
}

